payslip/admin.py
payslip/apps.py
payslip/forms.py
payslip/models.py
payslip/signals.py
payslip/tests.py
payslip/urls.py
payslip/views.py
payslip/migrations/0001_initial.py
payslip/migrations/__init__.py
payslip/migrations/__pycache__/0001_initial.cpython-310.pyc
payslip/migrations/__pycache__/__init__.cpython-310.pyc
payslip/templates/payslip/detail.html
payslip/templates/payslip/emp_list.html
payslip/templates/payslip/form.html
payslip/templates/payslip/list.html
payslip/views/__init__.py
payslip/views/payslip_m.py
payslip/views/payslip_v.py
payslip/views/__pycache__/__init__.cpython-310.pyc
payslip/views/__pycache__/__init__.cpython-37.pyc
payslip/views/__pycache__/__init__.cpython-39.pyc
payslip/views/__pycache__/payslip_m.cpython-310.pyc
payslip/views/__pycache__/payslip_m.cpython-37.pyc
payslip/views/__pycache__/payslip_m.cpython-39.pyc
payslip/views/__pycache__/payslip_v.cpython-310.pyc
payslip/views/__pycache__/payslip_v.cpython-37.pyc
payslip/views/__pycache__/payslip_v.cpython-39.pyc
django_ipghrms_payslip-1.0.dist-info/LICENSE
django_ipghrms_payslip-1.0.dist-info/METADATA
django_ipghrms_payslip-1.0.dist-info/WHEEL
django_ipghrms_payslip-1.0.dist-info/top_level.txt
django_ipghrms_payslip-1.0.dist-info/RECORD
